pylsf/__init__.py
pylsf/available_resources.py
pylsf/cli.py
pylsf-0.1.0.dist-info/METADATA
pylsf-0.1.0.dist-info/WHEEL
pylsf-0.1.0.dist-info/entry_points.txt
pylsf-0.1.0.dist-info/RECORD
